confidentblackbox/__init__.py
confidentblackbox-0.0.1.dev0.dist-info/LICENSE
confidentblackbox-0.0.1.dev0.dist-info/METADATA
confidentblackbox-0.0.1.dev0.dist-info/WHEEL
confidentblackbox-0.0.1.dev0.dist-info/top_level.txt
confidentblackbox-0.0.1.dev0.dist-info/RECORD
